{
  "$schema": "https://json-schema.org/draft/2020-12/schema",
  "$id": "https://schemas.schofield.local/epic-d/TransformsCatalogItem.json",
  "title": "TransformsCatalogItem",
  "type": "object",
  "properties": {
    "transform_id": {
      "type": "string"
    },
    "name": {
      "type": "string"
    },
    "answer_kind": {
      "$ref": "https://schemas.schofield.local/epic-d/AnswerKind.json"
    },
    "supports_options": {
      "type": "boolean"
    },
    "notes": {
      "type": "string"
    }
  },
  "required": [
    "transform_id",
    "name",
    "answer_kind",
    "supports_options"
  ],
  "additionalProperties": false
}